pycrx/__init__.py
pycrx/test.py
PyCRX-0.0.6969.dist-info/LICENSE
PyCRX-0.0.6969.dist-info/METADATA
PyCRX-0.0.6969.dist-info/WHEEL
PyCRX-0.0.6969.dist-info/top_level.txt
PyCRX-0.0.6969.dist-info/RECORD
