Metadata-Version: 2.1
Name: PyCRX
Version: 0.0.6969
Summary: Used for functions in PyCRX OS
Home-page: https://replit.com/@cr1tical/PyCRXpkg?monaco=1
Author: Cr1tical
Author-email: critical@criticalfn.ml
License: UNKNOWN
Platform: UNKNOWN
Classifier: Programming Language :: Python :: 3
Classifier: License :: OSI Approved :: MIT License
Classifier: Operating System :: OS Independent
Requires-Python: >=3.6
License-File: LICENSE
